sprite_gpu/__init__.py
sprite_gpu/_version.py
sprite_gpu/concurrency.py
sprite_gpu/conf.py
sprite_gpu/env.py
sprite_gpu/log.py
sprite_gpu/manager.py
sprite_gpu/server.py
sprite_gpu/settings.py
sprite_gpu/task.py
sprite_gpu/worker.py
sprite_gpu/utils/__init__.py
sprite_gpu/utils/file.py
sprite_gpu/utils/validate.py
sprite_gpu-0.0.6.dist-info/LICENSE
sprite_gpu-0.0.6.dist-info/METADATA
sprite_gpu-0.0.6.dist-info/WHEEL
sprite_gpu-0.0.6.dist-info/top_level.txt
sprite_gpu-0.0.6.dist-info/RECORD
