Metadata-Version: 2.1
Name: sprite-gpu
Version: 0.0.6
Summary: Python serverless framework for Datastone Sprite GPU.
Home-page: https://github.com/datastone-sprite
Author: Sprite
Author-email: Sprite <pypi@datastone.cn>
License: MIT License
Project-URL: Homepage, https://github.com/datastone-sprite
Project-URL: Documentation, https://github.com/datastone-sprite/sprite-gpu/blob/main/README.md
Project-URL: Repository, https://github.com/datastone-sprite/sprite-gpu
Project-URL: BugTracker, https://github.com/datastone-sprite/sprite-gpu/issues
Keywords: serverless,ai,gpu,machine learning,SDK,library,python,API
Classifier: Topic :: Software Development :: Libraries :: Application Frameworks
Classifier: License :: OSI Approved :: MIT License
Classifier: Programming Language :: Python :: 3.9
Classifier: Operating System :: OS Independent
Classifier: Environment :: GPU
Requires-Python: >=3.9
License-File: LICENSE
Requires-Dist: requests>=2.31.0
Requires-Dist: PyYAML>=6.0.1
Requires-Dist: backoff>=2.2.1
Requires-Dist: aiohttp>=3.9.1
Requires-Dist: pydantic>=2.5.2
Provides-Extra: test
Requires-Dist: pytest; extra == "test"
